[{
    "name": "lev3lup",
    "report": 8
    
  },{
    "name": "WTN",
    "report": 3
    
  },{
    "name": "DarkPwners",
    "report": 4
    
  },{
    "name": "PAM",
    "report": 16
    
  },{
    "name": "B1n4ry B0y5",
    "report": 3
    
  },{
    "name": "Duty",
    "report": 44
    
  },{
    "name": "Repeater",
    "report": 4
    
  },{
    "name": "flag motori",
    "report": 0
    
  },{
    "name": "Disqualified",
    "report": 9
    
  },{
    "name": "me_name",
    "report": 2
    
  },{
    "name": "Sleepyheads",
    "report": 1
    
  },{
    "name": "silent",
    "report": 5
    
  },{
    "name": "Hades",
    "report": 8
    
  },{
    "name": "HexTor",
    "report": 4
    
  }]
